setup.py
easy_rest/__init__.py
easy_rest/rest.py
easy_rest/rest_dsl.py
easyrest.egg-info/PKG-INFO
easyrest.egg-info/SOURCES.txt
easyrest.egg-info/dependency_links.txt
easyrest.egg-info/not-zip-safe
easyrest.egg-info/top_level.txt