Metadata-Version: 1.0
Name: easyrest
Version: 0.1.7
Summary: Wrap python urllib to quickly access Rest API
Home-page: https://github.com/unklhe/easy-rest
Author: Eric He
Author-email: unklhe@gmail.com
License: ASL 2.0
Platform: UNKNOWN
